CHANGES.rst
CONTRIBUTORS.rst
MANIFEST.in
README.rst
setup.cfg
setup.py
docs/LICENSE.GPL
docs/LICENSE.txt
src/interlegis/__init__.py
src/interlegis.portalmodelo.api.egg-info/PKG-INFO
src/interlegis.portalmodelo.api.egg-info/SOURCES.txt
src/interlegis.portalmodelo.api.egg-info/dependency_links.txt
src/interlegis.portalmodelo.api.egg-info/entry_points.txt
src/interlegis.portalmodelo.api.egg-info/namespace_packages.txt
src/interlegis.portalmodelo.api.egg-info/not-zip-safe
src/interlegis.portalmodelo.api.egg-info/requires.txt
src/interlegis.portalmodelo.api.egg-info/top_level.txt
src/interlegis/portalmodelo/__init__.py
src/interlegis/portalmodelo/api/__init__.py
src/interlegis/portalmodelo/api/browser.py
src/interlegis/portalmodelo/api/config.py
src/interlegis/portalmodelo/api/configure.zcml
src/interlegis/portalmodelo/api/controlpanel.py
src/interlegis/portalmodelo/api/interfaces.py
src/interlegis/portalmodelo/api/profiles.zcml
src/interlegis/portalmodelo/api/testing.py
src/interlegis/portalmodelo/api/utils.py
src/interlegis/portalmodelo/api/Extensions/Install.py
src/interlegis/portalmodelo/api/Extensions/__init__.py
src/interlegis/portalmodelo/api/locales/interlegis.portalmodelo.api.pot
src/interlegis/portalmodelo/api/locales/manual.pot
src/interlegis/portalmodelo/api/locales/plone.pot
src/interlegis/portalmodelo/api/locales/pt_BR/LC_MESSAGES/interlegis.portalmodelo.api.po
src/interlegis/portalmodelo/api/locales/pt_BR/LC_MESSAGES/plone.po
src/interlegis/portalmodelo/api/profiles/default/browserlayer.xml
src/interlegis/portalmodelo/api/profiles/default/controlpanel.xml
src/interlegis/portalmodelo/api/profiles/default/metadata.xml
src/interlegis/portalmodelo/api/profiles/default/registry.xml
src/interlegis/portalmodelo/api/profiles/uninstall/registry.xml
src/interlegis/portalmodelo/api/static/interlegis.png
src/interlegis/portalmodelo/api/static/interlegis_icon.png
src/interlegis/portalmodelo/api/tests/__init__.py
src/interlegis/portalmodelo/api/tests/test_controlpanel.py
src/interlegis/portalmodelo/api/tests/test_controlpanel.robot
src/interlegis/portalmodelo/api/tests/test_robot.py
src/interlegis/portalmodelo/api/tests/test_setup.py
src/interlegis/portalmodelo/api/upgrades/__init__.py
src/interlegis/portalmodelo/api/upgrades/configure.zcml
src/interlegis/portalmodelo/api/upgrades/v1010/__init__.py
src/interlegis/portalmodelo/api/upgrades/v1010/configure.zcml
